django2_propeller/__init__.py
django2_propeller/apps.py
django2_propeller/card.py
django2_propeller/components.py
django2_propeller/exceptions.py
django2_propeller/forms.py
django2_propeller/models.py
django2_propeller/navbar.py
django2_propeller/propeller.py
django2_propeller/renderers.py
django2_propeller/test_data.py
django2_propeller/test_results.py
django2_propeller/tests.py
django2_propeller/text.py
django2_propeller/utils.py
django2_propeller/views.py
django2_propeller/__pycache__/__init__.cpython-37.pyc
django2_propeller/__pycache__/card.cpython-37.pyc
django2_propeller/__pycache__/components.cpython-37.pyc
django2_propeller/__pycache__/exceptions.cpython-37.pyc
django2_propeller/__pycache__/forms.cpython-37.pyc
django2_propeller/__pycache__/models.cpython-37.pyc
django2_propeller/__pycache__/navbar.cpython-37.pyc
django2_propeller/__pycache__/propeller.cpython-37.pyc
django2_propeller/__pycache__/renderers.cpython-37.pyc
django2_propeller/__pycache__/test_data.cpython-37.pyc
django2_propeller/__pycache__/test_results.cpython-37.pyc
django2_propeller/__pycache__/tests.cpython-37.pyc
django2_propeller/__pycache__/text.cpython-37.pyc
django2_propeller/__pycache__/utils.cpython-37.pyc
django2_propeller/__pycache__/views.cpython-37.pyc
django2_propeller/migrations/__init__.py
django2_propeller/migrations/__pycache__/__init__.cpython-37.pyc
django2_propeller/static/css/propeller.min.css
django2_propeller/static/css/propeller.min.css.map
django2_propeller/static/fonts/roboto/Roboto-Black-webfont.eot
django2_propeller/static/fonts/roboto/Roboto-Black-webfont.svg
django2_propeller/static/fonts/roboto/Roboto-Black-webfont.ttf
django2_propeller/static/fonts/roboto/Roboto-Black-webfont.woff
django2_propeller/static/fonts/roboto/Roboto-Bold-webfont.eot
django2_propeller/static/fonts/roboto/Roboto-Bold-webfont.svg
django2_propeller/static/fonts/roboto/Roboto-Bold-webfont.ttf
django2_propeller/static/fonts/roboto/Roboto-Bold-webfont.woff
django2_propeller-2.0.1.dist-info/LICENSE
django2_propeller-2.0.1.dist-info/METADATA
django2_propeller-2.0.1.dist-info/WHEEL
django2_propeller-2.0.1.dist-info/top_level.txt
django2_propeller-2.0.1.dist-info/RECORD
